prisma_helpers/__init__.py
prisma_helpers/graphql_connection.py
prisma_helpers/prisma_helpers.py
prisma_helpers/prisma_query_builders.py
tests/__init__.py
prisma_helpers-0.1.3.dist-info/LICENSE
prisma_helpers-0.1.3.dist-info/METADATA
prisma_helpers-0.1.3.dist-info/WHEEL
prisma_helpers-0.1.3.dist-info/top_level.txt
prisma_helpers-0.1.3.dist-info/RECORD
